ifunnygifmaker/__init__.py
ifunnygifmaker/fonts/Futura Condensed Extra Bold.otf
ifunnygifmaker/mememaker.py
ifunnygifmaker/utils/image_utils.py
ifunnygifmaker-1.0.3.dist-info/WHEEL
ifunnygifmaker-1.0.3.dist-info/METADATA
ifunnygifmaker-1.0.3.dist-info/RECORD
