Metadata-Version: 2.1
Name: ifunnygifmaker
Version: 1.0.3
License: MIT
Author-email: jaypyles <jpylesbusiness@gmail.com>
Requires-Python: >=3.9
Requires-Dist: pillow==9.5.0
Requires-Dist: python-dotenv>=1.0.0
Requires-Dist: requests>=2.28.2
